cosyvoice_mcp/__init__.py
cosyvoice_mcp/main.py
cosyvoice_mcp-0.6.0.dist-info/licenses/LICENSE
cosyvoice_mcp-0.6.0.dist-info/METADATA
cosyvoice_mcp-0.6.0.dist-info/WHEEL
cosyvoice_mcp-0.6.0.dist-info/entry_points.txt
cosyvoice_mcp-0.6.0.dist-info/top_level.txt
cosyvoice_mcp-0.6.0.dist-info/RECORD
