Metadata-Version: 2.4
Name: cosyvoice-mcp
Version: 0.6.0
Summary: A MCP server for CosyVoice TTS using DashScope API
Home-page: https://github.com/chenjin3/cosyvoice-mcp
Author: Marlon Chan
Author-email: yuxian.cj@alibaba-inc.com
Classifier: Programming Language :: Python :: 3
Classifier: License :: OSI Approved :: MIT License
Classifier: Operating System :: OS Independent
Requires-Python: >=3.8
License-File: LICENSE
Requires-Dist: fastmcp>=2.5.1
Requires-Dist: dashscope>=1.23.0
Requires-Dist: pydantic>=2.6.0
Requires-Dist: mutagen>=1.40.0
Dynamic: author
Dynamic: author-email
Dynamic: classifier
Dynamic: description
Dynamic: description-content-type
Dynamic: home-page
Dynamic: license-file
Dynamic: requires-dist
Dynamic: requires-python
Dynamic: summary
